pyfortool/__init__.py
pyfortool/applications.py
pyfortool/cosmetics.py
pyfortool/cpp.py
pyfortool/expressions.py
pyfortool/openacc.py
pyfortool/pyfortool.py
pyfortool/scope.py
pyfortool/scripting.py
pyfortool/statements.py
pyfortool/tree.py
pyfortool/util.py
pyfortool/variables.py
pyfortool-0.2.9.dist-info/licenses/LICENSE
pyfortool-0.2.9.dist-info/METADATA
pyfortool-0.2.9.dist-info/WHEEL
pyfortool-0.2.9.dist-info/entry_points.txt
pyfortool-0.2.9.dist-info/top_level.txt
pyfortool-0.2.9.dist-info/RECORD
