Metadata-Version: 2.4
Name: pyfortool
Version: 0.2.9
Summary: Python-fortran-tool
Author-email: Quentin Rodier <quentin.rodier@meteo.fr>, Sébastien Riette <sebastien.riette@meteo.Fr>
License: LICENSE
Project-URL: Repository, https://github.com/UMR-CNRM/pyfortool
Project-URL: Documentation, https://umr-cnrm.github.io/pyfortool
Project-URL: Issues, https://github.com/UMR-CNRM/pyfortool/issues
Keywords: fortran,static-analysis
Classifier: Programming Language :: Python :: 3
Classifier: License :: CeCILL-C Free Software License Agreement (CECILL-C)
Classifier: Operating System :: POSIX :: Linux
Requires-Python: >=3.8
License-File: LICENSE
Requires-Dist: pyfxtran>=0.1.3
Dynamic: license-file
